Workbook
Name Contagem_de_Gender: C̳álculos!#REF!
Name EA_Play_Season_Pass: C̳álculos!$C$15
Name Gender: C̳álculos!$C$35
Name Minecraft__season_Pass_Price: C̳álculos!$C$56
Name Minecraft_Season_Pass_Price: C̳álculos!$C$27
Name SegmentaçãodeDados_Subscription_Type1: #N/A
Name Soma_de_Minecraft_Season_Pass_Price: C̳álculos!#REF!
Name Soma_de_Total_Value: C̳álculos!$C$8

Sheet A̳ssets
B3: Paleta de Cores
B5: # 9BC848 | C5: Xbox Color | E5: # E8E6E9 | F5: negative zone
B6: # 22C55E | C6: Xbox Color
B7: # 2AE6B1 | C7: Menus
B8: # 5BF6A8 | C8: Menus
B12: Logos | J12: ícones

Sheet B̳ases
A1: Subscriber ID | B1: Name | C1: Name2 | D1: Coluna1 | E1: Gender | F1: Plan | G1: Start Date | H1: Auto Renewal | I1: Subscription Price | J1: Subscription Type | K1: EA Play Season Pass | L1: EA Play Season Pass Price | M1: Minecraft Season Pass | N1: Minecraft Season Pass Price | O1: Coupon Value | P1: Total Value | Q1: valor_Liquido
A2: 3231 | B2: João | C2: =_xlfn.CONCAT(B̳ases!$B2," ",B̳ases!$D2) -> João Silva | D2: Silva | E2: Masculino | F2: Ultimate | G2: 45292 | H2: Yes | I2: 15 | J2: Monthly | K2: Yes | L2: 30 | M2: Yes | N2: 20 | O2: 5 | P2: 60 | Q2: =P2-O2 -> 55 | R2: 1
A3: 3232 | B3: Maria | C3: =_xlfn.CONCAT(B̳ases!$B3,B̳ases!$D3) -> MariaOliveira | D3: Oliveira | E3: Feminino | F3: Core | G3: 45306 | H3: No | I3: 5 | J3: Annual | K3: No | M3: No | N3: 0 | O3: 0 | P3: 5 | Q3: =P3-O3 -> 5
A4: 3233 | B4: Lucas | C4: =_xlfn.CONCAT(B̳ases!$B4," ",B̳ases!$D4) -> Lucas Fernandes | D4: Fernandes | E4: Masculino | F4: Standard | G4: 45332 | H4: Yes | I4: 10 | J4: Quarterly | K4: No | M4: Yes | N4: 20 | O4: 10 | P4: 20 | Q4: =P4-O4 -> 10
A5: 3234 | B5: Ana | C5: =_xlfn.CONCAT(B̳ases!$B5,B̳ases!$D5) -> AnaSouza | D5: Souza | E5: Feminino | F5: Ultimate | G5: 45342 | H5: No | I5: 15 | J5: Monthly | K5: Yes | L5: 30 | M5: Yes | N5: 20 | O5: 3 | P5: 62 | Q5: =P5-O5 -> 59
A6: 3235 | B6: Pedro | C6: =_xlfn.CONCAT(B̳ases!$B6," ",B̳ases!$D6) -> Pedro Gonçalves | D6: Gonçalves | E6: Masculino | F6: Core | G6: 45356 | H6: Yes | I6: 5 | J6: Monthly | K6: No | M6: No | N6: 0 | O6: 1 | P6: 4 | Q6: =P6-O6 -> 3
A7: 3236 | B7: Felipe | C7: =_xlfn.CONCAT(B̳ases!$B7," ",B̳ases!$D7) -> Felipe Costa | D7: Costa | E7: Masculino | F7: Standard | G7: 45353 | H7: No | I7: 10 | J7: Monthly | K7: No | M7: Yes | N7: 20 | O7: 2 | P7: 28 | Q7: =P7-O7 -> 26
A8: 3237 | B8: Camila | C8: =_xlfn.CONCAT(B̳ases!$B8,B̳ases!$D8) -> CamilaRibeiro | D8: Ribeiro | E8: Feminino | F8: Ultimate | G8: 45354 | H8: Yes | I8: 15 | J8: Quarterly | K8: Yes | L8: 30 | M8: Yes | N8: 20 | O8: 10 | P8: 55 | Q8: =P8-O8 -> 45
A9: 3238 | B9: André | C9: =_xlfn.CONCAT(B̳ases!$B9," ",B̳ases!$D9) -> André Mendes | D9: Mendes | E9: Masculino | F9: Core | G9: 45355 | H9: Yes | I9: 5 | J9: Annual | K9: No | M9: No | N9: 0 | O9: 0 | P9: 5 | Q9: =P9-O9 -> 5
A10: 3239 | B10: Sofia | C10: =_xlfn.CONCAT(B̳ases!$B10,B̳ases!$D10) -> SofiaAlmeida | D10: Almeida | E10: Feminino | F10: Ultimate | G10: 45356 | H10: No | I10: 15 | J10: Monthly | K10: Yes | L10: 30 | M10: Yes | N10: 20 | O10: 5 | P10: 60 | Q10: =P10-O10 -> 55
A11: 3240 | B11: Bruno | C11: =_xlfn.CONCAT(B̳ases!$B11," ",B̳ases!$D11) -> Bruno Martins | D11: Martins | E11: Masculino | F11: Standard | G11: 45357 | H11: Yes | I11: 10 | J11: Quarterly | K11: No | M11: Yes | N11: 20 | O11: 15 | P11: 15 | Q11: =P11-O11 -> 0
A12: 3241 | B12: Rita | C12: =_xlfn.CONCAT(B̳ases!$B12,B̳ases!$D12) -> RitaCastro | D12: Castro | E12: Feminino | F12: Core | G12: 45358 | H12: No | I12: 5 | J12: Monthly | K12: No | M12: No | N12: 0 | O12: 1 | P12: 4 | Q12: =P12-O12 -> 3
A13: 3242 | B13: Marco | C13: =_xlfn.CONCAT(B̳ases!$B13," ",B̳ases!$D13) -> Marco Túlio | D13: Túlio | E13: Masculino | F13: Ultimate | G13: 45359 | H13: Yes | I13: 15 | J13: Annual | K13: Yes | L13: 30 | M13: Yes | N13: 20 | O13: 20 | P13: 45 | Q13: =P13-O13 -> 25
A14: 3243 | B14: Lívia | C14: =_xlfn.CONCAT(B̳ases!$B14,B̳ases!$D14) -> LíviaSilveira | D14: Silveira | E14: Feminino | F14: Standard | G14: 45360 | H14: No | I14: 10 | J14: Monthly | K14: No | M14: Yes | N14: 20 | O14: 10 | P14: 20 | Q14: =P14-O14 -> 10
A15: 3244 | B15: Diogo | C15: =_xlfn.CONCAT(B̳ases!$B15," ",B̳ases!$D15) -> Diogo Sousa | D15: Sousa | E15: Masculino | F15: Core | G15: 45361 | H15: Yes | I15: 5 | J15: Quarterly | K15: No | M15: No | N15: 0 | O15: 0 | P15: 5 | Q15: =P15-O15 -> 5
A16: 3245 | B16: Fernanda | C16: =_xlfn.CONCAT(B̳ases!$B16,B̳ases!$D16) -> FernandaLima | D16: Lima | E16: Feminino | F16: Ultimate | G16: 45362 | H16: No | I16: 15 | J16: Monthly | K16: Yes | L16: 30 | M16: Yes | N16: 20 | O16: 8 | P16: 57 | Q16: =P16-O16 -> 49
A17: 3246 | B17: Caio | C17: =_xlfn.CONCAT(B̳ases!$B17," ",B̳ases!$D17) -> Caio Pereira | D17: Pereira | E17: Masculino | F17: Standard | G17: 45363 | H17: Yes | I17: 10 | J17: Annual | K17: No | M17: Yes | N17: 20 | O17: 12 | P17: 18 | Q17: =P17-O17 -> 6
A18: 3247 | B18: Beatriz | C18: =_xlfn.CONCAT(B̳ases!$B18," ",B̳ases!$D18) -> Beatriz Gomes | D18: Gomes | E18: Feminino | F18: Core | G18: 45364 | H18: No | I18: 5 | J18: Monthly | K18: No | M18: No | N18: 0 | O18: 2 | P18: 3 | Q18: =P18-O18 -> 1
A19: 3248 | B19: Cesar | C19: =_xlfn.CONCAT(B̳ases!$B19," ",B̳ases!$D19) -> Cesar Oliveira | D19: Oliveira | E19: Masculino | F19: Ultimate | G19: 45365 | H19: Yes | I19: 15 | J19: Quarterly | K19: Yes | L19: 30 | M19: Yes | N19: 20 | O19: 7 | P19: 58 | Q19: =P19-O19 -> 51
A20: 3249 | B20: Débora | C20: =_xlfn.CONCAT(B̳ases!$B20,B̳ases!$D20) -> DéboraMachado | D20: Machado | E20: Feminino | F20: Standard | G20: 45366 | H20: No | I20: 10 | J20: Monthly | K20: No | M20: Yes | N20: 20 | O20: 5 | P20: 25 | Q20: =P20-O20 -> 20
A21: 3250 | B21: Eduardo | C21: =_xlfn.CONCAT(B̳ases!$B21," ",B̳ases!$D21) -> Eduardo Vargas | D21: Vargas | E21: Masculino | F21: Core | G21: 45367 | H21: Yes | I21: 5 | J21: Annual | K21: No | M21: No | N21: 0 | O21: 0 | P21: 5 | Q21: =P21-O21 -> 5
A22: 3251 | B22: Gabriela | C22: =_xlfn.CONCAT(B̳ases!$B22,B̳ases!$D22) -> GabrielaSantos | D22: Santos | E22: Feminino | F22: Ultimate | G22: 45368 | H22: No | I22: 15 | J22: Monthly | K22: Yes | L22: 30 | M22: Yes | N22: 20 | O22: 3 | P22: 62 | Q22: =P22-O22 -> 59
A23: 3252 | B23: Henrique | C23: =_xlfn.CONCAT(B̳ases!$B23," ",B̳ases!$D23) -> Henrique Dias | D23: Dias | E23: Masculino | F23: Standard | G23: 45369 | H23: Yes | I23: 10 | J23: Quarterly | K23: No | M23: Yes | N23: 20 | O23: 15 | P23: 15 | Q23: =P23-O23 -> 0
A24: 3253 | B24: Isabela | C24: =_xlfn.CONCAT(B̳ases!$B24,B̳ases!$D24) -> IsabelaMoreira | D24: Moreira | E24: Feminino | F24: Core | G24: 45370 | H24: No | I24: 5 | J24: Monthly | K24: No | M24: No | N24: 0 | O24: 1 | P24: 4 | Q24: =P24-O24 -> 3
A25: 3254 | B25: Joaquim | C25: =_xlfn.CONCAT(B̳ases!$B25," ",B̳ases!$D25) -> Joaquim Barbosa | D25: Barbosa | E25: Masculino | F25: Ultimate | G25: 45371 | H25: Yes | I25: 15 | J25: Annual | K25: Yes | L25: 30 | M25: Yes | N25: 20 | O25: 20 | P25: 45 | Q25: =P25-O25 -> 25
A26: 3255 | B26: Lara | C26: =_xlfn.CONCAT(B̳ases!$B26,B̳ases!$D26) -> LaraRocha | D26: Rocha | E26: Feminino | F26: Standard | G26: 45372 | H26: No | I26: 10 | J26: Monthly | K26: No | M26: Yes | N26: 20 | O26: 10 | P26: 20 | Q26: =P26-O26 -> 10
A27: 3256 | B27: Matheus | C27: =_xlfn.CONCAT(B̳ases!$B27," ",B̳ases!$D27) -> Matheus Silva | D27: Silva | E27: Masculino | F27: Core | G27: 45373 | H27: Yes | I27: 5 | J27: Quarterly | K27: No | M27: No | N27: 0 | O27: 0 | P27: 5 | Q27: =P27-O27 -> 5
A28: 3257 | B28: Nicole | C28: =_xlfn.CONCAT(B̳ases!$B28," ",B̳ases!$D28) -> Nicole Costa | D28: Costa | E28: Feminino | F28: Ultimate | G28: 45374 | H28: No | I28: 15 | J28: Monthly | K28: Yes | L28: 30 | M28: Yes | N28: 20 | O28: 5 | P28: 60 | Q28: =P28-O28 -> 55
A29: 3258 | B29: Otávio | C29: =_xlfn.CONCAT(B̳ases!$B29," ",B̳ases!$D29) -> Otávio Mendonça | D29: Mendonça | E29: Masculino | F29: Standard | G29: 45375 | H29: Yes | I29: 10 | J29: Annual | K29: No | M29: Yes | N29: 20 | O29: 15 | P29: 15 | Q29: =P29-O29 -> 0
A30: 3259 | B30: Paula | C30: =_xlfn.CONCAT(B̳ases!$B30,B̳ases!$D30) -> PaulaFerreira | D30: Ferreira | E30: Feminino | F30: Core | G30: 45376 | H30: No | I30: 5 | J30: Monthly | K30: No | M30: No | N30: 0 | O30: 1 | P30: 4 | Q30: =P30-O30 -> 3
A31: 3260 | B31: Raquel | C31: =_xlfn.CONCAT(B̳ases!$B31," ",B̳ases!$D31) -> Raquel Alves | D31: Alves | E31: Feminino | F31: Ultimate | G31: 45377 | H31: Yes | I31: 15 | J31: Quarterly | K31: Yes | L31: 30 | M31: Yes | N31: 20 | O31: 7 | P31: 58 | Q31: =P31-O31 -> 51
A32: 3261 | B32: Samuel | C32: =_xlfn.CONCAT(B̳ases!$B32," ",B̳ases!$D32) -> Samuel Pires | D32: Pires | E32: Masculino | F32: Standard | G32: 45378 | H32: No | I32: 10 | J32: Monthly | K32: No | M32: Yes | N32: 20 | O32: 10 | P32: 20 | Q32: =P32-O32 -> 10
A33: 3262 | B33: Tânia | C33: =_xlfn.CONCAT(B̳ases!$B33,B̳ases!$D33) -> TâniaBarros | D33: Barros | E33: Feminino | F33: Core | G33: 45379 | H33: Yes | I33: 5 | J33: Annual | K33: No | M33: No | N33: 0 | O33: 0 | P33: 5 | Q33: =P33-O33 -> 5
A34: 3263 | B34: Vinicius | C34: =_xlfn.CONCAT(B̳ases!$B34," ",B̳ases!$D34) -> Vinicius Lima | D34: Lima | E34: Masculino | F34: Ultimate | G34: 45380 | H34: No | I34: 15 | J34: Monthly | K34: Yes | L34: 30 | M34: Yes | N34: 20 | O34: 3 | P34: 62 | Q34: =P34-O34 -> 59
A35: 3264 | B35: Yasmin | C35: =_xlfn.CONCAT(B̳ases!$B35," ",B̳ases!$D35) -> Yasmin Teixeira | D35: Teixeira | E35: Feminino | F35: Standard | G35: 45381 | H35: Yes | I35: 10 | J35: Quarterly | K35: No | M35: Yes | N35: 20 | O35: 15 | P35: 15 | Q35: =P35-O35 -> 0
A36: 3265 | B36: Zé | C36: =_xlfn.CONCAT(B̳ases!$B36," ",B̳ases!$D36) -> Zé Carlos | D36: Carlos | E36: Masculino | F36: Core | G36: 45382 | H36: No | I36: 5 | J36: Monthly | K36: No | M36: No | N36: 0 | O36: 1 | P36: 4 | Q36: =P36-O36 -> 3
A37: 3266 | B37: Amanda | C37: =_xlfn.CONCAT(B̳ases!$B37,B̳ases!$D37) -> AmandaNogueira | D37: Nogueira | E37: Feminino | F37: Core | G37: 45383 | H37: Yes | I37: 5 | J37: Monthly | K37: No | M37: No | N37: 0 | O37: 0 | P37: 5 | Q37: =P37-O37 -> 5
A38: 3267 | B38: Bruno | C38: =_xlfn.CONCAT(B̳ases!$B38," ",B̳ases!$D38) -> Bruno Cavalheiro | D38: Cavalheiro | E38: Masculino | F38: Ultimate | G38: 45384 | H38: No | I38: 15 | J38: Quarterly | K38: Yes | L38: 30 | M38: Yes | N38: 20 | O38: 7 | P38: 58 | Q38: =P38-O38 -> 51
A39: 3268 | B39: Carla | C39: =_xlfn.CONCAT(B̳ases!$B39,B̳ases!$D39) -> CarlaDias | D39: Dias | E39: Feminino | F39: Standard | G39: 45385 | H39: Yes | I39: 10 | J39: Annual | K39: No | M39: Yes | N39: 20 | O39: 10 | P39: 20 | Q39: =P39-O39 -> 10
A40: 3269 | B40: Diego | C40: =_xlfn.CONCAT(B̳ases!$B40," ",B̳ases!$D40) -> Diego Fontes | D40: Fontes | E40: Masculino | F40: Core | G40: 45386 | H40: No | I40: 5 | J40: Quarterly | K40: No | M40: No | N40: 0 | O40: 1 | P40: 4 | Q40: =P40-O40 -> 3
A41: 3270 | B41: Eunice | C41: =_xlfn.CONCAT(B̳ases!$B41," ",B̳ases!$D41) -> Eunice Lima | D41: Lima | E41: Feminino | F41: Ultimate | G41: 45387 | H41: Yes | I41: 15 | J41: Monthly | K41: Yes | L41: 30 | M41: Yes | N41: 20 | O41: 15 | P41: 50 | Q41: =P41-O41 -> 35
A42: 3271 | B42: Fábio | C42: =_xlfn.CONCAT(B̳ases!$B42," ",B̳ases!$D42) -> Fábio Martins | D42: Martins | E42: Masculino | F42: Standard | G42: 45388 | H42: No | I42: 10 | J42: Monthly | K42: No | M42: Yes | N42: 20 | O42: 5 | P42: 25 | Q42: =P42-O42 -> 20
A43: 3272 | B43: Gisele | C43: =_xlfn.CONCAT(B̳ases!$B43," ",B̳ases!$D43) -> Gisele Araújo | D43: Araújo | E43: Feminino | F43: Core | G43: 45389 | H43: Yes | I43: 5 | J43: Annual | K43: No | M43: No | N43: 0 | O43: 0 | P43: 5 | Q43: =P43-O43 -> 5
A44: 3273 | B44: Hélio | C44: =_xlfn.CONCAT(B̳ases!$B44," ",B̳ases!$D44) -> Hélio Castro | D44: Castro | E44: Masculino | F44: Ultimate | G44: 45390 | H44: No | I44: 15 | J44: Quarterly | K44: Yes | L44: 30 | M44: Yes | N44: 20 | O44: 20 | P44: 45 | Q44: =P44-O44 -> 25
A45: 3274 | B45: Ingrid | C45: =_xlfn.CONCAT(B̳ases!$B45," ",B̳ases!$D45) -> Ingrid Menezes | D45: Menezes | E45: Feminino | F45: Standard | G45: 45391 | H45: Yes | I45: 10 | J45: Quarterly | K45: No | M45: Yes | N45: 20 | O45: 12 | P45: 18 | Q45: =P45-O45 -> 6
A46: 3275 | B46: Jorge | C46: =_xlfn.CONCAT(B̳ases!$B46," ",B̳ases!$D46) -> Jorge Baptista | D46: Baptista | E46: Masculino | F46: Core | G46: 45392 | H46: No | I46: 5 | J46: Monthly | K46: No | M46: No | N46: 0 | O46: 2 | P46: 3 | Q46: =P46-O46 -> 1
A47: 3276 | B47: Kléber | C47: =_xlfn.CONCAT(B̳ases!$B47," ",B̳ases!$D47) -> Kléber Oliveira | D47: Oliveira | E47: Masculino | F47: Ultimate | G47: 45393 | H47: Yes | I47: 15 | J47: Annual | K47: Yes | L47: 30 | M47: Yes | N47: 20 | O47: 5 | P47: 60 | Q47: =P47-O47 -> 55
A48: 3277 | B48: Luciana | C48: =_xlfn.CONCAT(B̳ases!$B48,B̳ases!$D48) -> LucianaFreitas | D48: Freitas | E48: Feminino | F48: Standard | G48: 45394 | H48: No | I48: 10 | J48: Monthly | K48: No | M48: Yes | N48: 20 | O48: 10 | P48: 20 | Q48: =P48-O48 -> 10
A49: 3278 | B49: Márcia | C49: =_xlfn.CONCAT(B̳ases!$B49,B̳ases!$D49) -> MárciaEller | D49: Eller | E49: Feminino | F49: Core | G49: 45395 | H49: Yes | I49: 5 | J49: Quarterly | K49: No | M49: No | N49: 0 | O49: 0 | P49: 5 | Q49: =P49-O49 -> 5
A50: 3279 | B50: Nilo | C50: =_xlfn.CONCAT(B̳ases!$B50," ",B̳ases!$D50) -> Nilo Peçanha | D50: Peçanha | E50: Masculino | F50: Ultimate | G50: 45396 | H50: No | I50: 15 | J50: Monthly | K50: Yes | L50: 30 | M50: Yes | N50: 20 | O50: 3 | P50: 62 | Q50: =P50-O50 -> 59
A51: 3280 | B51: Oscar | C51: =_xlfn.CONCAT(B̳ases!$B51," ",B̳ases!$D51) -> Oscar Neves | D51: Neves | E51: Masculino | F51: Standard | G51: 45397 | H51: Yes | I51: 10 | J51: Annual | K51: No | M51: Yes | N51: 20 | O51: 15 | P51: 15 | Q51: =P51-O51 -> 0
A52: 3281 | B52: Patrícia | C52: =_xlfn.CONCAT(B̳ases!$B52,B̳ases!$D52) -> PatríciaSoares | D52: Soares | E52: Feminino | F52: Core | G52: 45398 | H52: No | I52: 5 | J52: Monthly | K52: No | M52: No | N52: 0 | O52: 1 | P52: 4 | Q52: =P52-O52 -> 3
A53: 3282 | B53: Quirino | C53: =_xlfn.CONCAT(B̳ases!$B53," ",B̳ases!$D53) -> Quirino Gonçalves | D53: Gonçalves | E53: Masculino | F53: Ultimate | G53: 45399 | H53: Yes | I53: 15 | J53: Quarterly | K53: Yes | L53: 30 | M53: Yes | N53: 20 | O53: 7 | P53: 58 | Q53: =P53-O53 -> 51
A54: 3283 | B54: Raul | C54: =_xlfn.CONCAT(B̳ases!$B54," ",B̳ases!$D54) -> Raul Machado | D54: Machado | E54: Masculino | F54: Standard | G54: 45400 | H54: No | I54: 10 | J54: Monthly | K54: No | M54: Yes | N54: 20 | O54: 10 | P54: 20 | Q54: =P54-O54 -> 10
A55: 3284 | B55: Sônia | C55: =_xlfn.CONCAT(B̳ases!$B55,B̳ases!$D55) -> SôniaLobo | D55: Lobo | E55: Feminino | F55: Core | G55: 45401 | H55: Yes | I55: 5 | J55: Annual | K55: No | M55: No | N55: 0 | O55: 0 | P55: 5 | Q55: =P55-O55 -> 5
A56: 3285 | B56: Tiago | C56: =_xlfn.CONCAT(B̳ases!$B56," ",B̳ases!$D56) -> Tiago Ramos | D56: Ramos | E56: Masculino | F56: Ultimate | G56: 45402 | H56: No | I56: 15 | J56: Monthly | K56: Yes | L56: 30 | M56: Yes | N56: 20 | O56: 20 | P56: 45 | Q56: =P56-O56 -> 25
A57: 3286 | B57: Ugo | C57: =_xlfn.CONCAT(B̳ases!$B57," ",B̳ases!$D57) -> Ugo Pires | D57: Pires | E57: Masculino | F57: Standard | G57: 45403 | H57: Yes | I57: 10 | J57: Quarterly | K57: No | M57: Yes | N57: 20 | O57: 15 | P57: 15 | Q57: =P57-O57 -> 0
A58: 3287 | B58: Valéria | C58: =_xlfn.CONCAT(B̳ases!$B58,B̳ases!$D58) -> ValériaNobre | D58: Nobre | E58: Feminino | F58: Core | G58: 45404 | H58: No | I58: 5 | J58: Monthly | K58: No | M58: No | N58: 0 | O58: 1 | P58: 4 | Q58: =P58-O58 -> 3
A59: 3288 | B59: William | C59: =_xlfn.CONCAT(B̳ases!$B59," ",B̳ases!$D59) -> William Siqueira | D59: Siqueira | E59: Masculino | F59: Ultimate | G59: 45405 | H59: Yes | I59: 15 | J59: Annual | K59: Yes | L59: 30 | M59: Yes | N59: 20 | O59: 3 | P59: 62 | Q59: =P59-O59 -> 59
A60: 3289 | B60: Xuxa | C60: =_xlfn.CONCAT(B̳ases!$B60,B̳ases!$D60) -> XuxaMeneghel | D60: Meneghel | E60: Feminino | F60: Standard | G60: 45406 | H60: No | I60: 10 | J60: Monthly | K60: No | M60: Yes | N60: 20 | O60: 10 | P60: 20 | Q60: =P60-O60 -> 10
A61: 3290 | B61: Yara | C61: =_xlfn.CONCAT(B̳ases!$B61,B̳ases!$D61) -> YaraFigueiredo | D61: Figueiredo | E61: Feminino | F61: Core | G61: 45407 | H61: Yes | I61: 5 | J61: Quarterly | K61: No | M61: No | N61: 0 | O61: 0 | P61: 5 | Q61: =P61-O61 -> 5
A62: 3291 | B62: Zacarias | C62: =_xlfn.CONCAT(B̳ases!$B62," ",B̳ases!$D62) -> Zacarias Alves | D62: Alves | E62: Masculino | F62: Ultimate | G62: 45408 | H62: No | I62: 15 | J62: Monthly | K62: Yes | L62: 30 | M62: Yes | N62: 20 | O62: 5 | P62: 60 | Q62: =P62-O62 -> 55
A63: 3292 | B63: Amanda | C63: =_xlfn.CONCAT(B̳ases!$B63,B̳ases!$D63) -> AmandaBynes | D63: Bynes | E63: Feminino | F63: Standard | G63: 45409 | H63: Yes | I63: 10 | J63: Annual | K63: No | M63: Yes | N63: 20 | O63: 15 | P63: 15 | Q63: =P63-O63 -> 0
A64: 3293 | B64: Bruno | C64: =_xlfn.CONCAT(B̳ases!$B64," ",B̳ases!$D64) -> Bruno Mars | D64: Mars | E64: Masculino | F64: Core | G64: 45410 | H64: No | I64: 5 | J64: Monthly | K64: No | M64: No | N64: 0 | O64: 1 | P64: 4 | Q64: =P64-O64 -> 3
A65: 3294 | B65: Carla | C65: =_xlfn.CONCAT(B̳ases!$B65,B̳ases!$D65) -> CarlaBruni | D65: Bruni | E65: Feminino | F65: Ultimate | G65: 45411 | H65: Yes | I65: 15 | J65: Quarterly | K65: Yes | L65: 30 | M65: Yes | N65: 20 | O65: 20 | P65: 45 | Q65: =P65-O65 -> 25
A66: 3295 | B66: Diego | C66: =_xlfn.CONCAT(B̳ases!$B66," ",B̳ases!$D66) -> Diego Maradona | D66: Maradona | E66: Masculino | F66: Standard | G66: 45412 | H66: No | I66: 10 | J66: Monthly | K66: No | M66: Yes | N66: 20 | O66: 5 | P66: 25 | Q66: =P66-O66 -> 20
A67: 3296 | B67: Estela | C67: =_xlfn.CONCAT(B̳ases!$B67,B̳ases!$D67) -> EstelaMarques | D67: Marques | E67: Feminino | F67: Core | G67: 45413 | H67: No | I67: 5 | J67: Monthly | K67: No | M67: No | N67: 0 | O67: 0 | P67: 5 | Q67: =P67-O67 -> 5
A68: 3297 | B68: Fábio | C68: =_xlfn.CONCAT(B̳ases!$B68," ",B̳ases!$D68) -> Fábio Nobre | D68: Nobre | E68: Masculino | F68: Ultimate | G68: 45414 | H68: Yes | I68: 15 | J68: Quarterly | K68: Yes | L68: 30 | M68: Yes | N68: 20 | O68: 7 | P68: 58 | Q68: =P68-O68 -> 51
A69: 3298 | B69: Gabriel | C69: =_xlfn.CONCAT(B̳ases!$B69," ",B̳ases!$D69) -> Gabriel Oliveira | D69: Oliveira | E69: Masculino | F69: Standard | G69: 45415 | H69: No | I69: 10 | J69: Annual | K69: No | M69: Yes | N69: 20 | O69: 10 | P69: 20 | Q69: =P69-O69 -> 10
A70: 3299 | B70: Helena | C70: =_xlfn.CONCAT(B̳ases!$B70,B̳ases!$D70) -> HelenaSantos | D70: Santos | E70: Feminino | F70: Core | G70: 45416 | H70: Yes | I70: 5 | J70: Quarterly | K70: No | M70: No | N70: 0 | O70: 1 | P70: 4 | Q70: =P70-O70 -> 3
A71: 3300 | B71: Ivan | C71: =_xlfn.CONCAT(B̳ases!$B71," ",B̳ases!$D71) -> Ivan Carvalho | D71: Carvalho | E71: Masculino | F71: Ultimate | G71: 45417 | H71: No | I71: 15 | J71: Monthly | K71: Yes | L71: 30 | M71: Yes | N71: 20 | O71: 15 | P71: 50 | Q71: =P71-O71 -> 35
A72: 3301 | B72: Júlia | C72: =_xlfn.CONCAT(B̳ases!$B72,B̳ases!$D72) -> JúliaFerreira | D72: Ferreira | E72: Feminino | F72: Standard | G72: 45418 | H72: Yes | I72: 10 | J72: Monthly | K72: No | M72: Yes | N72: 20 | O72: 5 | P72: 25 | Q72: =P72-O72 -> 20
A73: 3302 | B73: Karla | C73: =_xlfn.CONCAT(B̳ases!$B73,B̳ases!$D73) -> KarlaAlves | D73: Alves | E73: Feminino | F73: Core | G73: 45419 | H73: No | I73: 5 | J73: Annual | K73: No | M73: No | N73: 0 | O73: 0 | P73: 5 | Q73: =P73-O73 -> 5
A74: 3303 | B74: Lucas | C74: =_xlfn.CONCAT(B̳ases!$B74," ",B̳ases!$D74) -> Lucas Mendes | D74: Mendes | E74: Masculino | F74: Ultimate | G74: 45420 | H74: Yes | I74: 15 | J74: Quarterly | K74: Yes | L74: 30 | M74: Yes | N74: 20 | O74: 20 | P74: 45 | Q74: =P74-O74 -> 25
A75: 3304 | B75: Mônica | C75: =_xlfn.CONCAT(B̳ases!$B75,B̳ases!$D75) -> MônicaGomes | D75: Gomes | E75: Feminino | F75: Standard | G75: 45421 | H75: No | I75: 10 | J75: Quarterly | K75: No | M75: Yes | N75: 20 | O75: 12 | P75: 18 | Q75: =P75-O75 -> 6
A76: 3305 | B76: Norberto | C76: =_xlfn.CONCAT(B̳ases!$B76," ",B̳ases!$D76) -> Norberto Queiroz | D76: Queiroz | E76: Masculino | F76: Core | G76: 45422 | H76: Yes | I76: 5 | J76: Monthly | K76: No | M76: No | N76: 0 | O76: 2 | P76: 3 | Q76: =P76-O76 -> 1
A77: 3306 | B77: Otávio | C77: =_xlfn.CONCAT(B̳ases!$B77," ",B̳ases!$D77) -> Otávio Barros | D77: Barros | E77: Masculino | F77: Ultimate | G77: 45423 | H77: No | I77: 15 | J77: Annual | K77: Yes | L77: 30 | M77: Yes | N77: 20 | O77: 5 | P77: 60 | Q77: =P77-O77 -> 55
A78: 3307 | B78: Paula | C78: =_xlfn.CONCAT(B̳ases!$B78,B̳ases!$D78) -> PaulaVieira | D78: Vieira | E78: Feminino | F78: Standard | G78: 45424 | H78: Yes | I78: 10 | J78: Monthly | K78: No | M78: Yes | N78: 20 | O78: 10 | P78: 20 | Q78: =P78-O78 -> 10
A79: 3308 | B79: Quentin | C79: =_xlfn.CONCAT(B̳ases!$B79," ",B̳ases!$D79) -> Quentin Ramos | D79: Ramos | E79: Masculino | F79: Core | G79: 45425 | H79: No | I79: 5 | J79: Quarterly | K79: No | M79: No | N79: 0 | O79: 0 | P79: 5 | Q79: =P79-O79 -> 5
A80: 3309 | B80: Raquel | C80: =_xlfn.CONCAT(B̳ases!$B80," ",B̳ases!$D80) -> Raquel Novaes | D80: Novaes | E80: Feminino | F80: Ultimate | G80: 45426 | H80: Yes | I80: 15 | J80: Monthly | K80: Yes | L80: 30 | M80: Yes | N80: 20 | O80: 3 | P80: 62 | Q80: =P80-O80 -> 59
A81: 3310 | B81: Samantha | C81: =_xlfn.CONCAT(B̳ases!$B81,B̳ases!$D81) -> SamanthaLopes | D81: Lopes | E81: Feminino | F81: Standard | G81: 45427 | H81: No | I81: 10 | J81: Annual | K81: No | M81: Yes | N81: 20 | O81: 15 | P81: 15 | Q81: =P81-O81 -> 0
A82: 3311 | B82: Tiago | C82: =_xlfn.CONCAT(B̳ases!$B82," ",B̳ases!$D82) -> Tiago Martins | D82: Martins | E82: Masculino | F82: Core | G82: 45428 | H82: Yes | I82: 5 | J82: Monthly | K82: No | M82: No | N82: 0 | O82: 1 | P82: 4 | Q82: =P82-O82 -> 3
A83: 3312 | B83: Ulysses | C83: =_xlfn.CONCAT(B̳ases!$B83," ",B̳ases!$D83) -> Ulysses Guimarães | D83: Guimarães | E83: Masculino | F83: Ultimate | G83: 45429 | H83: No | I83: 15 | J83: Quarterly | K83: Yes | L83: 30 | M83: Yes | N83: 20 | O83: 7 | P83: 58 | Q83: =P83-O83 -> 51
A84: 3313 | B84: Vanessa | C84: =_xlfn.CONCAT(B̳ases!$B84,B̳ases!$D84) -> VanessaSilva | D84: Silva | E84: Feminino | F84: Standard | G84: 45430 | H84: Yes | I84: 10 | J84: Monthly | K84: No | M84: Yes | N84: 20 | O84: 10 | P84: 20 | Q84: =P84-O84 -> 10
A85: 3314 | B85: William | C85: =_xlfn.CONCAT(B̳ases!$B85," ",B̳ases!$D85) -> William Carneiro | D85: Carneiro | E85: Masculino | F85: Core | G85: 45431 | H85: No | I85: 5 | J85: Annual | K85: No | M85: No | N85: 0 | O85: 0 | P85: 5 | Q85: =P85-O85 -> 5
A86: 3315 | B86: Ximena | C86: =_xlfn.CONCAT(B̳ases!$B86,B̳ases!$D86) -> XimenaRocha | D86: Rocha | E86: Feminino | F86: Ultimate | G86: 45432 | H86: Yes | I86: 15 | J86: Monthly | K86: Yes | L86: 30 | M86: Yes | N86: 20 | O86: 20 | P86: 45 | Q86: =P86-O86 -> 25
A87: 3316 | B87: Yasmin | C87: =_xlfn.CONCAT(B̳ases!$B87," ",B̳ases!$D87) -> Yasmin Figueiredo | D87: Figueiredo | E87: Feminino | F87: Standard | G87: 45433 | H87: No | I87: 10 | J87: Quarterly | K87: No | M87: Yes | N87: 20 | O87: 15 | P87: 15 | Q87: =P87-O87 -> 0
A88: 3317 | B88: Zara | C88: =_xlfn.CONCAT(B̳ases!$B88,B̳ases!$D88) -> ZaraCunha | D88: Cunha | E88: Feminino | F88: Core | G88: 45434 | H88: Yes | I88: 5 | J88: Monthly | K88: No | M88: No | N88: 0 | O88: 1 | P88: 4 | Q88: =P88-O88 -> 3
A89: 3318 | B89: Alan | C89: =_xlfn.CONCAT(B̳ases!$B89," ",B̳ases!$D89) -> Alan Teixeira | D89: Teixeira | E89: Masculino | F89: Ultimate | G89: 45435 | H89: No | I89: 15 | J89: Annual | K89: Yes | L89: 30 | M89: Yes | N89: 20 | O89: 3 | P89: 62 | Q89: =P89-O89 -> 59
A90: 3319 | B90: Bárbara | C90: =_xlfn.CONCAT(B̳ases!$B90,B̳ases!$D90) -> BárbaraOliveira | D90: Oliveira | E90: Feminino | F90: Standard | G90: 45436 | H90: Yes | I90: 10 | J90: Monthly | K90: No | M90: Yes | N90: 20 | O90: 10 | P90: 20 | Q90: =P90-O90 -> 10
A91: 3320 | B91: Carlos | C91: =_xlfn.CONCAT(B̳ases!$B91," ",B̳ases!$D91) -> Carlos Junqueira | D91: Junqueira | E91: Masculino | F91: Core | G91: 45437 | H91: No | I91: 5 | J91: Quarterly | K91: No | M91: No | N91: 0 | O91: 0 | P91: 5 | Q91: =P91-O91 -> 5
A92: 3321 | B92: Daniela | C92: =_xlfn.CONCAT(B̳ases!$B92,B̳ases!$D92) -> DanielaMoura | D92: Moura | E92: Feminino | F92: Ultimate | G92: 45438 | H92: Yes | I92: 15 | J92: Monthly | K92: Yes | L92: 30 | M92: Yes | N92: 20 | O92: 5 | P92: 60 | Q92: =P92-O92 -> 55
A93: 3322 | B93: Eduardo | C93: =_xlfn.CONCAT(B̳ases!$B93," ",B̳ases!$D93) -> Eduardo Lima | D93: Lima | E93: Masculino | F93: Standard | G93: 45439 | H93: No | I93: 10 | J93: Annual | K93: No | M93: Yes | N93: 20 | O93: 15 | P93: 15 | Q93: =P93-O93 -> 0
A94: 3323 | B94: Fabiana | C94: =_xlfn.CONCAT(B̳ases!$B94,B̳ases!$D94) -> FabianaAraújo | D94: Araújo | E94: Feminino | F94: Core | G94: 45440 | H94: Yes | I94: 5 | J94: Monthly | K94: No | M94: No | N94: 0 | O94: 1 | P94: 4 | Q94: =P94-O94 -> 3
A95: 3324 | B95: Geraldo | C95: =_xlfn.CONCAT(B̳ases!$B95," ",B̳ases!$D95) -> Geraldo Ribeiro | D95: Ribeiro | E95: Masculino | F95: Ultimate | G95: 45441 | H95: No | I95: 15 | J95: Quarterly | K95: Yes | L95: 30 | M95: Yes | N95: 20 | O95: 20 | P95: 45 | Q95: =P95-O95 -> 25
A96: 3325 | B96: Héctor | C96: =_xlfn.CONCAT(B̳ases!$B96," ",B̳ases!$D96) -> Héctor Vargas | D96: Vargas | E96: Masculino | F96: Standard | G96: 45442 | H96: Yes | I96: 10 | J96: Quarterly | K96: No | M96: Yes | N96: 20 | O96: 15 | P96: 15 | Q96: =P96-O96 -> 0
A97: 3326 | B97: Isabela | C97: =_xlfn.CONCAT(B̳ases!$B97,B̳ases!$D97) -> IsabelaFonseca | D97: Fonseca | E97: Feminino | F97: Core | G97: 45443 | H97: No | I97: 5 | J97: Annual | K97: No | M97: No | N97: 0 | O97: 0 | P97: 5 | Q97: =P97-O97 -> 5
A98: 3327 | B98: João | C98: =_xlfn.CONCAT(B̳ases!$B98," ",B̳ases!$D98) -> João Pedro Almeida | D98: Pedro Almeida | E98: Masculino | F98: Ultimate | G98: 45444 | H98: Yes | I98: 15 | J98: Monthly | K98: Yes | L98: 30 | M98: Yes | N98: 20 | O98: 7 | P98: 58 | Q98: =P98-O98 -> 51
A99: 3328 | B99: Klara | C99: =_xlfn.CONCAT(B̳ases!$B99,B̳ases!$D99) -> KlaraCosta | D99: Costa | E99: Feminino | F99: Standard | G99: 45445 | H99: No | I99: 10 | J99: Annual | K99: No | M99: Yes | N99: 20 | O99: 10 | P99: 20 | Q99: =P99-O99 -> 10
A100: 3329 | B100: Luciana | C100: =_xlfn.CONCAT(B̳ases!$B100,B̳ases!$D100) -> LucianaMendes | D100: Mendes | E100: Feminino | F100: Core | G100: 45446 | H100: Yes | I100: 5 | J100: Quarterly | K100: No | M100: No | N100: 0 | O100: 1 | P100: 4 | Q100: =P100-O100 -> 3
...

Sheet Planilha1
A1: Subscription Type | B1: All
A3: Rótulos de Linha | B3: Soma de Coupon Value | C3: Soma de Total Value | D3: Soma de Total Value2
A4: Core | B4: 61 | C4: 444 | D4: 444
A5: Standard | B5: 1079 | C5: 1801 | D5: 1801
A6: Ultimate | B6: 982 | C6: 5388 | D6: 5388
A7: Total Geral | B7: 2122 | C7: 7633 | D7: 7633

Sheet C̳álculos
B2: Pergunta de Negócio 1: Qual faturamento Total de vendas de planos anuais (contendo todas as assinaturas agregadas).
B3: Pergunta de Negócio 2: Qual faturamento Total de vendas de planos anuais separado por renovação não é por auto renovação.
B6: Subscription Type | C6: Annual
B8: Rótulos de Linha | C8: Soma de Total Value
B9: No | C9: 217
B10: Yes | C10: 1537
B11: Total Geral | C11: 1754 | D11: =GETPIVOTDATA("[Measures].[Soma de Total Value 3]",$B$8) -> 1754
B13: Pergunta Negócio 3: Total de vendas de assinaturas do EA Play
B15: Subscription Type | C15: Annual
B17: Rótulos de Linha | C17: Soma de EA Play Season Pass Price
B18: Ultimate | C18: 600
B19: Total Geral | C19: 600 | D19: =GETPIVOTDATA("[Measures].[Soma de EA Play Season Pass Price]",$B$17) -> 600
B23: Pergunta Negócio 4: Total de vendas de assinaturas do Season Pass Price
B24: Subscription Type | C24: Annual
B26: Rótulos de Linha | C26: Soma de Minecraft Season Pass Price
B27: Core | C27: 0
B28: Standard | C28: 540
B29: Ultimate | C29: 400
B30: Total Geral | C30: 940 | D30: =GETPIVOTDATA("[Measures].[Soma de Minecraft Season Pass Price]",$B$26) -> 940
B33: Pergunta Negócio 5: Qual genero que mais consome os produtos?
B36: Rótulos de Linha | C36: Contagem de Gender
B37: Feminino | C37: 34
B38: Masculino | C38: 37
B39: Total Geral | C39: 71
B41: Pergunta Negócio 6: Qual o total de descontos, Lucro total e Lucro liquído?
B42: Subscription Type | C42: Annual
B44: Rótulos de Linha | C44: Coupon_Value | D44: Total_Value | E44: Valor_Liquido
B45: Core | C45: 0 | D45: 120 | E45: 120
B46: Standard | C46: 362 | D46: 448 | E46: 86
B47: Ultimate | C47: 114 | D47: 1186 | E47: 1072
B48: Total Geral | C48: 476 | D48: 1754 | E48: 1278
B52: Pergunta Negócio 7: Qual o ticket médio por cliente?
B54: Subscription Type | C54: Annual
B56: Rótulos de Linha | C56: Média de Total Value
B57: Core | C57: 5
B58: Standard | C58: 16.592593
B59: Ultimate | C59: 59.3
B60: Total Geral | C60: 24.704225

Sheet D̳ashboard
D2: XBOX GAME PASS SUBSCRIPTIONS SALES
A4: > Bem vindo, Felipe | C4: Calculation period: 25/03/2025 - 25/03/2026 | Update date: 25/03/2026 15:00:00
